{
  "meta": {
    "generatedAt": "2026-04-01T08:04:16.414Z",
    "totalFiles": 7,
    "totalIssues": 36,
    "summary": {
      "accessibility": 2,
      "design-token-mismatch": 11,
      "missing-property": 6,
      "rtl-directional-property": 16,
      "rtl-text-align": 1
    }
  },
  "issues": [
    {
      "file": "src/demo/buttons.scss",
      "type": "design-token-mismatch",
      "severity": "error",
      "component": "Primary Button",
      "element": "Button",
      "selector": ".ds-btn--primary",
      "state": "Default",
      "property": "background-color",
      "expected": "var(--Surface-Brand, #2563eb)",
      "found": "$brand-color",
      "message": "[Primary Button / Button] \"background-color\" expected \"var(--Surface-Brand, #2563eb)\", found \"$brand-color\""
    },
    {
      "file": "src/demo/buttons.scss",
      "type": "design-token-mismatch",
      "severity": "error",
      "component": "Primary Button",
      "element": "Button",
      "selector": ".ds-btn--primary",
      "state": "Default",
      "property": "background-color",
      "expected": "var(--Surface-Brand, #2563eb)",
      "found": "$brand-disabled",
      "message": "[Primary Button / Button] \"background-color\" expected \"var(--Surface-Brand, #2563eb)\", found \"$brand-disabled\""
    },
    {
      "file": "src/demo/buttons.scss",
      "type": "design-token-mismatch",
      "severity": "error",
      "component": "Primary Button",
      "element": "Button",
      "selector": ".ds-btn--primary",
      "state": "Default",
      "property": "background-color",
      "expected": "var(--Surface-Brand, #2563eb)",
      "found": "$brand-hover",
      "message": "[Primary Button / Button] \"background-color\" expected \"var(--Surface-Brand, #2563eb)\", found \"$brand-hover\""
    },
    {
      "file": "src/demo/buttons.scss",
      "type": "design-token-mismatch",
      "severity": "error",
      "component": "Secondary Button",
      "element": "Button",
      "selector": ".ds-btn--secondary",
      "state": "Default",
      "property": "color",
      "expected": "var(--Text-Brand, #2563eb)",
      "found": "$secondary-color",
      "message": "[Secondary Button / Button] \"color\" expected \"var(--Text-Brand, #2563eb)\", found \"$secondary-color\""
    },
    {
      "file": "src/demo/buttons.scss",
      "type": "rtl-directional-property",
      "severity": "warning",
      "property": "padding-left",
      "value": "20px",
      "line": 13,
      "suggestion": "padding-inline-start",
      "message": "\"padding-left\" should be \"padding-inline-start\" for RTL support (line 13)"
    },
    {
      "file": "src/demo/buttons.scss",
      "type": "rtl-directional-property",
      "severity": "warning",
      "property": "padding-left",
      "value": "20px",
      "line": 39,
      "suggestion": "padding-inline-start",
      "message": "\"padding-left\" should be \"padding-inline-start\" for RTL support (line 39)"
    },
    {
      "file": "src/demo/buttons.scss",
      "type": "rtl-directional-property",
      "severity": "warning",
      "property": "padding-right",
      "value": "20px",
      "line": 14,
      "suggestion": "padding-inline-end",
      "message": "\"padding-right\" should be \"padding-inline-end\" for RTL support (line 14)"
    },
    {
      "file": "src/demo/buttons.scss",
      "type": "rtl-directional-property",
      "severity": "warning",
      "property": "padding-right",
      "value": "20px",
      "line": 40,
      "suggestion": "padding-inline-end",
      "message": "\"padding-right\" should be \"padding-inline-end\" for RTL support (line 40)"
    },
    {
      "file": "src/demo/cards.css",
      "type": "design-token-mismatch",
      "severity": "error",
      "component": "Card Header",
      "element": "Card Heading Text",
      "selector": ".ds-card__heading",
      "state": "Default",
      "property": "color",
      "expected": "var(--Text-Primary, #111827)",
      "found": "#FF0000",
      "message": "[Card Header / Card Heading Text] \"color\" expected \"var(--Text-Primary, #111827)\", found \"#FF0000\""
    },
    {
      "file": "src/demo/cards.css",
      "type": "rtl-directional-property",
      "severity": "warning",
      "property": "padding-left",
      "value": "24px",
      "line": 6,
      "suggestion": "padding-inline-start",
      "message": "\"padding-left\" should be \"padding-inline-start\" for RTL support (line 6)"
    },
    {
      "file": "src/demo/cards.css",
      "type": "rtl-directional-property",
      "severity": "warning",
      "property": "padding-right",
      "value": "24px",
      "line": 7,
      "suggestion": "padding-inline-end",
      "message": "\"padding-right\" should be \"padding-inline-end\" for RTL support (line 7)"
    },
    {
      "file": "src/demo/cards.css",
      "type": "rtl-text-align",
      "severity": "warning",
      "property": "text-align",
      "value": "left",
      "line": 33,
      "suggestion": "start",
      "message": "\"text-align: left\" should be \"text-align: start\" for RTL support (line 33)"
    },
    {
      "file": "src/demo/forms.css",
      "type": "design-token-mismatch",
      "severity": "error",
      "component": "Text Field",
      "element": "Input Box",
      "selector": ".ds-text-field__input--error",
      "state": "Error",
      "property": "border-color",
      "expected": "var(--Stroke-Error, #BB1122)",
      "found": "#FF0000",
      "message": "[Text Field / Input Box] \"border-color\" expected \"var(--Stroke-Error, #BB1122)\", found \"#FF0000\""
    },
    {
      "file": "src/demo/forms.css",
      "type": "design-token-mismatch",
      "severity": "error",
      "component": "Dropdown",
      "element": "Dropdown Box",
      "selector": ".ds-dropdown__box",
      "state": "Default",
      "property": "border-radius",
      "expected": "4px",
      "found": "2px",
      "message": "[Dropdown / Dropdown Box] \"border-radius\" expected \"4px\", found \"2px\""
    },
    {
      "file": "src/demo/forms.css",
      "type": "design-token-mismatch",
      "severity": "error",
      "component": "Text Field",
      "element": "Label",
      "selector": ".ds-text-field__label",
      "state": "Default",
      "property": "color",
      "expected": "var(--Text-Primary, #001111)",
      "found": "#FF0000",
      "message": "[Text Field / Label] \"color\" expected \"var(--Text-Primary, #001111)\", found \"#FF0000\""
    },
    {
      "file": "src/demo/forms.css",
      "type": "missing-property",
      "severity": "error",
      "component": "Dropdown",
      "element": "Dropdown Box",
      "selector": ".ds-dropdown__box",
      "state": "Default",
      "property": "border-radius",
      "expected": "4px",
      "found": "missing",
      "message": "[Dropdown / Dropdown Box] \"border-radius\" not found in selector \".ds-dropdown__box\""
    },
    {
      "file": "src/demo/forms.css",
      "type": "missing-property",
      "severity": "error",
      "component": "Dropdown",
      "element": "Dropdown Box",
      "selector": ".ds-dropdown__box",
      "state": "Default",
      "property": "border-radius",
      "expected": "4px",
      "found": "missing",
      "message": "[Dropdown / Dropdown Box] \"border-radius\" not found in selector \".ds-dropdown__box\""
    },
    {
      "file": "src/demo/forms.css",
      "type": "rtl-directional-property",
      "severity": "warning",
      "property": "padding-left",
      "value": "12px",
      "line": 18,
      "suggestion": "padding-inline-start",
      "message": "\"padding-left\" should be \"padding-inline-start\" for RTL support (line 18)"
    },
    {
      "file": "src/demo/forms.css",
      "type": "rtl-directional-property",
      "severity": "warning",
      "property": "padding-left",
      "value": "2px",
      "line": 41,
      "suggestion": "padding-inline-start",
      "message": "\"padding-left\" should be \"padding-inline-start\" for RTL support (line 41)"
    },
    {
      "file": "src/demo/forms.css",
      "type": "rtl-directional-property",
      "severity": "warning",
      "property": "padding-left",
      "value": "12px",
      "line": 57,
      "suggestion": "padding-inline-start",
      "message": "\"padding-left\" should be \"padding-inline-start\" for RTL support (line 57)"
    },
    {
      "file": "src/demo/forms.css",
      "type": "rtl-directional-property",
      "severity": "warning",
      "property": "padding-left",
      "value": "2px",
      "line": 7,
      "suggestion": "padding-inline-start",
      "message": "\"padding-left\" should be \"padding-inline-start\" for RTL support (line 7)"
    },
    {
      "file": "src/demo/forms.css",
      "type": "rtl-directional-property",
      "severity": "warning",
      "property": "padding-right",
      "value": "12px",
      "line": 19,
      "suggestion": "padding-inline-end",
      "message": "\"padding-right\" should be \"padding-inline-end\" for RTL support (line 19)"
    },
    {
      "file": "src/demo/forms.css",
      "type": "rtl-directional-property",
      "severity": "warning",
      "property": "padding-right",
      "value": "12px",
      "line": 58,
      "suggestion": "padding-inline-end",
      "message": "\"padding-right\" should be \"padding-inline-end\" for RTL support (line 58)"
    },
    {
      "file": "src/demo/navigation.css",
      "type": "design-token-mismatch",
      "severity": "error",
      "component": "Header",
      "element": "Background",
      "selector": ".ds-navbar",
      "state": "Default",
      "property": "background-color",
      "expected": "var(--Surface-Brand, #2563eb)",
      "found": "#FF0000",
      "message": "[Header / Background] \"background-color\" expected \"var(--Surface-Brand, #2563eb)\", found \"#FF0000\""
    },
    {
      "file": "src/demo/navigation.css",
      "type": "design-token-mismatch",
      "severity": "error",
      "component": "Horizontal Tab",
      "element": "Active Tab",
      "selector": ".ds-tab__item--active",
      "state": "Default",
      "property": "border-bottom",
      "expected": "2px solid var(--Stroke-Brand, #2563eb)",
      "found": "2px solid #FF0000",
      "message": "[Horizontal Tab / Active Tab] \"border-bottom\" expected \"2px solid var(--Stroke-Brand, #2563eb)\", found \"2px solid #FF0000\""
    },
    {
      "file": "src/demo/navigation.css",
      "type": "design-token-mismatch",
      "severity": "error",
      "component": "Horizontal Tab",
      "element": "Active Tab",
      "selector": ".ds-tab__item--active",
      "state": "Default",
      "property": "color",
      "expected": "var(--Text-Brand, #2563eb)",
      "found": "#FF0000",
      "message": "[Horizontal Tab / Active Tab] \"color\" expected \"var(--Text-Brand, #2563eb)\", found \"#FF0000\""
    },
    {
      "file": "src/demo/navigation.css",
      "type": "missing-property",
      "severity": "error",
      "component": "Header",
      "element": "Background",
      "selector": ".ds-navbar",
      "state": "Default",
      "property": "background-color",
      "expected": "var(--Surface-Brand, #2563eb)",
      "found": "missing",
      "message": "[Header / Background] \"background-color\" not found in selector \".ds-navbar\""
    },
    {
      "file": "src/demo/navigation.css",
      "type": "missing-property",
      "severity": "error",
      "component": "Header",
      "element": "Background",
      "selector": ".ds-navbar",
      "state": "Default",
      "property": "background-color",
      "expected": "var(--Surface-Brand, #2563eb)",
      "found": "missing",
      "message": "[Header / Background] \"background-color\" not found in selector \".ds-navbar\""
    },
    {
      "file": "src/demo/navigation.css",
      "type": "missing-property",
      "severity": "error",
      "component": "Header",
      "element": "Background",
      "selector": ".ds-navbar",
      "state": "Default",
      "property": "background-color",
      "expected": "var(--Surface-Brand, #2563eb)",
      "found": "missing",
      "message": "[Header / Background] \"background-color\" not found in selector \".ds-navbar\""
    },
    {
      "file": "src/demo/navigation.css",
      "type": "missing-property",
      "severity": "error",
      "component": "Header",
      "element": "Background",
      "selector": ".ds-navbar",
      "state": "Default",
      "property": "background-color",
      "expected": "var(--Surface-Brand, #2563eb)",
      "found": "missing",
      "message": "[Header / Background] \"background-color\" not found in selector \".ds-navbar\""
    },
    {
      "file": "src/demo/navigation.css",
      "type": "rtl-directional-property",
      "severity": "warning",
      "property": "padding-left",
      "value": "24px",
      "line": 4,
      "suggestion": "padding-inline-start",
      "message": "\"padding-left\" should be \"padding-inline-start\" for RTL support (line 4)"
    },
    {
      "file": "src/demo/navigation.css",
      "type": "rtl-directional-property",
      "severity": "warning",
      "property": "padding-left",
      "value": "20px",
      "line": 49,
      "suggestion": "padding-inline-start",
      "message": "\"padding-left\" should be \"padding-inline-start\" for RTL support (line 49)"
    },
    {
      "file": "src/demo/navigation.css",
      "type": "rtl-directional-property",
      "severity": "warning",
      "property": "padding-right",
      "value": "24px",
      "line": 5,
      "suggestion": "padding-inline-end",
      "message": "\"padding-right\" should be \"padding-inline-end\" for RTL support (line 5)"
    },
    {
      "file": "src/demo/navigation.css",
      "type": "rtl-directional-property",
      "severity": "warning",
      "property": "padding-right",
      "value": "20px",
      "line": 50,
      "suggestion": "padding-inline-end",
      "message": "\"padding-right\" should be \"padding-inline-end\" for RTL support (line 50)"
    },
    {
      "file": "src/demo/page1-buttons.html",
      "type": "accessibility",
      "severity": "error",
      "message": "<html> element missing lang attribute"
    },
    {
      "file": "src/demo/page3-cards.html",
      "type": "accessibility",
      "severity": "error",
      "message": "<html> element missing lang attribute"
    }
  ]
}